hegel_ip_client/__init__.py
hegel_ip_client/client.py
hegel_ip_client/const.py
hegel_ip_client/exceptions.py
hegel_ip_client-0.1.4.dist-info/licenses/LICENSE
hegel_ip_client-0.1.4.dist-info/METADATA
hegel_ip_client-0.1.4.dist-info/WHEEL
hegel_ip_client-0.1.4.dist-info/top_level.txt
hegel_ip_client-0.1.4.dist-info/RECORD
