Metadata-Version: 2.4
Name: hegel-ip-client
Version: 0.1.4
Summary: Python client library for Hegel amplifiers
License: MIT
Project-URL: Homepage, https://github.com/boazca/hegel-ip-client
Project-URL: Bug Reports, https://github.com/boazca/hegel-ip-client/issues
Project-URL: Source, https://github.com/boazca/hegel-ip-client
Keywords: hegel,amplifier,audio,home-automation
Classifier: Development Status :: 4 - Beta
Classifier: Intended Audience :: Developers
Classifier: Operating System :: OS Independent
Classifier: Programming Language :: Python :: 3
Classifier: Programming Language :: Python :: 3.11
Classifier: Programming Language :: Python :: 3.12
Classifier: Topic :: Home Automation
Classifier: Topic :: Software Development :: Libraries :: Python Modules
Requires-Python: >=3.11
License-File: LICENSE
Dynamic: license-file
